nome/__init__.py
nome/application.py
nome/constants.py
nome/npm_command.py
nome/pypi_command.py
nome-0.1.0.dist-info/entry_points.txt
nome-0.1.0.dist-info/LICENSE
nome-0.1.0.dist-info/WHEEL
nome-0.1.0.dist-info/METADATA
nome-0.1.0.dist-info/RECORD
